minetest_log_parser/__init__.py
minetest_log_parser/Helpers/__init__.py
minetest_log_parser/Helpers/stringHelpers.py
minetest_log_parser/Parser/MinetestLogParser.py
minetest_log_parser/Parser/__init__.py
minetest_log_parser-0.0.2.dist-info/METADATA
minetest_log_parser-0.0.2.dist-info/WHEEL
minetest_log_parser-0.0.2.dist-info/top_level.txt
minetest_log_parser-0.0.2.dist-info/RECORD
