Metadata-Version: 2.1
Name: minetest-log-parser
Version: 0.0.2
Summary: Minetest player action log parser
Author-email: alwayshopeless <always.hopeless@protonmail.com>
Project-URL: Homepage, https://github.com/alwayshopeless/minetest-logs-parser
Project-URL: Bug Tracker, https://github.com/alwayshopeless/minetest-logs-parser/issues
Classifier: Programming Language :: Python :: 3
Classifier: License :: OSI Approved :: MIT License
Classifier: Operating System :: OS Independent
Requires-Python: >=3.11
